pinax/__init__.py
pinax/lms/__init__.py
pinax/lms/activities/__init__.py
pinax/lms/activities/admin.py
pinax/lms/activities/apps.py
pinax/lms/activities/base.py
pinax/lms/activities/conf.py
pinax/lms/activities/forms.py
pinax/lms/activities/hooks.py
pinax/lms/activities/models.py
pinax/lms/activities/proxies.py
pinax/lms/activities/signals.py
pinax/lms/activities/urls.py
pinax/lms/activities/utils.py
pinax/lms/activities/views.py
pinax/lms/activities/migrations/0001_initial.py
pinax/lms/activities/migrations/0002_auto_20160115_1726.py
pinax/lms/activities/migrations/0003_auto_20160115_2305.py
pinax/lms/activities/migrations/0004_auto_20160206_1021.py
pinax/lms/activities/migrations/0005_activitystate_activity_class_path.py
pinax/lms/activities/migrations/0006_auto_20160206_2029.py
pinax/lms/activities/migrations/0007_migrate.py
pinax/lms/activities/migrations/0008_schema_fix.py
pinax/lms/activities/migrations/0009_auto_20160207_2149.py
pinax/lms/activities/migrations/0010_auto_20160226_1751.py
pinax/lms/activities/migrations/__init__.py
pinax/lms/activities/templates/pinax/lms/activities/_answer.html
pinax/lms/activities/templates/pinax/lms/activities/_question.html
pinax/lms/activities/templates/pinax/lms/activities/activity.html
pinax/lms/activities/templates/pinax/lms/activities/base.html
pinax/lms/activities/templates/pinax/lms/activities/likert_quiz.html
pinax/lms/activities/templates/pinax/lms/activities/multiple_short_answer_quiz.html
pinax/lms/activities/templates/pinax/lms/activities/multiple_short_answer_quiz_completed.html
pinax/lms/activities/templates/pinax/lms/activities/order_quiz.html
pinax/lms/activities/templates/pinax/lms/activities/short_answer_quiz.html
pinax/lms/activities/templates/pinax/lms/activities/short_answer_quiz_completed.html
pinax/lms/activities/templates/pinax/lms/activities/staff_activity_detail.html
pinax/lms/activities/templates/pinax/lms/activities/staff_dashboard.html
pinax_lms_activities-0.18.0.dist-info/DESCRIPTION.rst
pinax_lms_activities-0.18.0.dist-info/METADATA
pinax_lms_activities-0.18.0.dist-info/RECORD
pinax_lms_activities-0.18.0.dist-info/WHEEL
pinax_lms_activities-0.18.0.dist-info/metadata.json
pinax_lms_activities-0.18.0.dist-info/top_level.txt
