Metadata-Version: 2.0
Name: pinax-lms-activities
Version: 0.18.0
Summary: framework and base learning activities for Pinax LMS
Home-page: http://pinax-lms-activities.rtfd.org/
Author: Pinax Developers
Author-email: developers@pinaxproject.com
License: MIT
Platform: UNKNOWN
Classifier: Development Status :: 4 - Beta
Classifier: Environment :: Web Environment
Classifier: Framework :: Django
Classifier: Intended Audience :: Developers
Classifier: License :: OSI Approved :: MIT License
Classifier: Operating System :: OS Independent
Classifier: Programming Language :: Python
Classifier: Programming Language :: Python :: 2
Classifier: Programming Language :: Python :: 3
Classifier: Topic :: Software Development :: Libraries :: Python Modules
Requires-Dist: django-appconf (>=1.0.1)
Requires-Dist: jsonfield (>=1.0.3)
Requires-Dist: pinax-eventlog (>=1.1.1)
